de/git_repo_manager.py
de_git_repo_manager-0.2.10.data/data/.gitignore
de_git_repo_manager-0.2.10.data/data/.gitlab-ci.yml
de_git_repo_manager-0.2.10.data/data/CONTRIBUTING.rst
de_git_repo_manager-0.2.10.data/data/LICENSE.md
de_git_repo_manager-0.2.10.data/data/SECURITY.md
de_git_repo_manager-0.2.10.data/data/coverage.svg
de_git_repo_manager-0.2.10.data/data/coverage.txt
de_git_repo_manager-0.2.10.data/data/dev_requirements.txt
de_git_repo_manager-0.2.10.data/data/requirements.txt
de_git_repo_manager-0.2.10.data/data/setup.cfg
de_git_repo_manager-0.2.10.data/data/setup.py
de_git_repo_manager-0.2.10.dist-info/LICENSE.md
de_git_repo_manager-0.2.10.dist-info/METADATA
de_git_repo_manager-0.2.10.dist-info/WHEEL
de_git_repo_manager-0.2.10.dist-info/entry_points.txt
de_git_repo_manager-0.2.10.dist-info/top_level.txt
de_git_repo_manager-0.2.10.dist-info/zip-safe
de_git_repo_manager-0.2.10.dist-info/RECORD
